splitstream.cpython-38-darwin.so
splitstream-1.2.6.data/headers/splitstream.h
splitstream-1.2.6.data/headers/splitstream_private.h
splitstream-1.2.6.dist-info/LICENSE
splitstream-1.2.6.dist-info/METADATA
splitstream-1.2.6.dist-info/WHEEL
splitstream-1.2.6.dist-info/top_level.txt
splitstream-1.2.6.dist-info/RECORD
